flask_mcp_server/__init__.py
flask_mcp_server/__version__.py
flask_mcp_server/caching.py
flask_mcp_server/cli.py
flask_mcp_server/container.py
flask_mcp_server/discovery.py
flask_mcp_server/events.py
flask_mcp_server/exceptions.py
flask_mcp_server/facade.py
flask_mcp_server/http_integrated.py
flask_mcp_server/logging_utils.py
flask_mcp_server/providers.py
flask_mcp_server/ratelimit.py
flask_mcp_server/registry.py
flask_mcp_server/resources.py
flask_mcp_server/schemas.py
flask_mcp_server/security.py
flask_mcp_server/server_http.py
flask_mcp_server/server_stdio.py
flask_mcp_server/sessions.py
flask_mcp_server/spec.py
flask_mcp_server/validation.py
flask_mcp_server-0.6.1.dist-info/METADATA
flask_mcp_server-0.6.1.dist-info/WHEEL
flask_mcp_server-0.6.1.dist-info/entry_points.txt
flask_mcp_server-0.6.1.dist-info/top_level.txt
flask_mcp_server-0.6.1.dist-info/RECORD
