Metadata-Version: 2.4
Name: flask-mcp-server
Version: 0.6.1
Summary: Flask-MCP-Server is a lightweight, production-ready Model Context Protocol (MCP) server for Flask, with tool discovery, endpoint registration, async support, and full compliance with the latest MCP 2025-06-18 specification.
Author-email: Bashar Bhuiyan <bbhuiyan1@gmail.com>
License: MIT
Project-URL: Homepage, https://github.com/bashar94/flask-mcp-server
Project-URL: Documentation, https://github.com/bashar94/flask-mcp-server/blob/main/README.md
Project-URL: Repository, https://github.com/bashar94/flask-mcp-server
Project-URL: Issues, https://github.com/bashar94/flask-mcp-server/issues
Requires-Python: >=3.9
Requires-Dist: Flask>=3.0.0
Requires-Dist: typer>=0.12.3
Requires-Dist: pydantic>=2.6.0
Requires-Dist: typing_extensions>=4.9.0
Requires-Dist: blinker>=1.8.0
Provides-Extra: redis
Requires-Dist: redis>=5.0.1; extra == "redis"
Provides-Extra: async
Requires-Dist: hypercorn>=0.16.0; extra == "async"
Provides-Extra: dev
Requires-Dist: pytest>=8.0.0; extra == "dev"
Requires-Dist: pytest-cov>=4.0.0; extra == "dev"
Requires-Dist: pytest-mock>=3.10.0; extra == "dev"
Requires-Dist: coverage>=7.0.0; extra == "dev"
